django2go/admin.py
django2go/apps.py
django2go/models.py
django2go/tests.py
django2go/views.py
django2go/__init__.py
django2go/management/__init__.py
django2go/management/commands/model2go.py
django2go/management/commands/__init__.py
django2go/migrations/__init__.py
django2go/templates/model.go
django2go-0.1.1.dist-info/DESCRIPTION.rst
django2go-0.1.1.dist-info/METADATA
django2go-0.1.1.dist-info/metadata.json
django2go-0.1.1.dist-info/RECORD
django2go-0.1.1.dist-info/top_level.txt
django2go-0.1.1.dist-info/WHEEL
